toolsets/__init__.py
toolsets/gradio_ui.py
toolsets/mcp_server.py
toolsets/package.json
toolsets/py.typed
toolsets/server.py
toolsets/toolset.py
toolsets/toolset_element.py
toolsets-0.1.9.dist-info/METADATA
toolsets-0.1.9.dist-info/WHEEL
toolsets-0.1.9.dist-info/licenses/LICENSE
toolsets-0.1.9.dist-info/RECORD
