Metadata-Version: 2.4
Name: toolsets
Version: 0.1.9
Summary: A Python toolsets library
Project-URL: homepage, https://github.com/your-org/your-repo
Project-URL: repository, https://github.com/your-org/your-repo
Author-email: Your Name <your.email@example.com>
License-File: LICENSE
Classifier: License :: OSI Approved :: MIT License
Classifier: Operating System :: OS Independent
Classifier: Programming Language :: Python :: 3
Requires-Python: >=3.10
Requires-Dist: gradio[mcp]>=6.0.0
Requires-Dist: httpx>=0.24.0
Provides-Extra: deferred
Requires-Dist: sentence-transformers>=2.2.0; extra == 'deferred'
Provides-Extra: dev
Requires-Dist: pytest-asyncio>=0.21.0; extra == 'dev'
Requires-Dist: pytest<9.0.0,>=8.0.0; extra == 'dev'
Requires-Dist: ruff==0.9.3; extra == 'dev'
